{
  "modoPert": true,
  "actividades": [
    {
      "id": "A",
      "prec": "-",
      "a": "4",
      "b": "6",
      "c": "8",
      "unico": "0",
      "calc": "6",
      "var": "0.44",
      "compTiempo": "4",
      "compCostoNormal": "1000",
      "compCostoComp": "1900"
    },
    {
      "id": "B",
      "prec": "-",
      "a": "6",
      "b": "8",
      "c": "16",
      "unico": "0",
      "calc": "9",
      "var": "2.78",
      "compTiempo": "7",
      "compCostoNormal": "1000",
      "compCostoComp": "1800"
    },
    {
      "id": "C",
      "prec": "A,B",
      "a": "2",
      "b": "4",
      "c": "6",
      "unico": "0",
      "calc": "4",
      "var": "0.44",
      "compTiempo": "2",
      "compCostoNormal": "1500",
      "compCostoComp": "2700"
    },
    {
      "id": "D",
      "prec": "C",
      "a": "8",
      "b": "10",
      "c": "24",
      "unico": "0",
      "calc": "12",
      "var": "7.11",
      "compTiempo": "8",
      "compCostoNormal": "2000",
      "compCostoComp": "3200"
    },
    {
      "id": "E",
      "prec": "C",
      "a": "7",
      "b": "10",
      "c": "13",
      "unico": "0",
      "calc": "10",
      "var": "1",
      "compTiempo": "7",
      "compCostoNormal": "5000",
      "compCostoComp": "8000"
    },
    {
      "id": "F",
      "prec": "E",
      "a": "4",
      "b": "6",
      "c": "8",
      "unico": "0",
      "calc": "6",
      "var": "0.44",
      "compTiempo": "4",
      "compCostoNormal": "3000",
      "compCostoComp": "4100"
    },
    {
      "id": "G",
      "prec": "C",
      "a": "4",
      "b": "6",
      "c": "20",
      "unico": "0",
      "calc": "8",
      "var": "7.11",
      "compTiempo": "5",
      "compCostoNormal": "8000",
      "compCostoComp": "10250"
    },
    {
      "id": "H",
      "prec": "D,F,G",
      "a": "4",
      "b": "6",
      "c": "8",
      "unico": "0",
      "calc": "6",
      "var": "0.44",
      "compTiempo": "4",
      "compCostoNormal": "5000",
      "compCostoComp": "6400"
    },
    {
      "id": "I",
      "prec": "D,F,G",
      "a": "4",
      "b": "6",
      "c": "14",
      "unico": "0",
      "calc": "7",
      "var": "2.78",
      "compTiempo": "4",
      "compCostoNormal": "10000",
      "compCostoComp": "12400"
    },
    {
      "id": "J",
      "prec": "H",
      "a": "3",
      "b": "4",
      "c": "5",
      "unico": "0",
      "calc": "4",
      "var": "0.11",
      "compTiempo": "3",
      "compCostoNormal": "4000",
      "compCostoComp": "4400"
    },
    {
      "id": "K",
      "prec": "I,J",
      "a": "2",
      "b": "4",
      "c": "6",
      "unico": "0",
      "calc": "4",
      "var": "0.44",
      "compTiempo": "3",
      "compCostoNormal": "5000",
      "compCostoComp": "5500"
    }
  ]
}